bytewax/bytewax_rerun/__init__.py
bytewax/bytewax_rerun/py.typed
bytewax/bytewax_rerun/sinks.py
bytewax_rerun-0.1.dist-info/LICENSE.md
bytewax_rerun-0.1.dist-info/METADATA
bytewax_rerun-0.1.dist-info/WHEEL
bytewax_rerun-0.1.dist-info/top_level.txt
bytewax_rerun-0.1.dist-info/RECORD
