Metadata-Version: 2.1
Name: bytewax-rerun
Version: 0.1
Summary: A Bytewax connector for Rerun
Author-email: "Bytewax, Inc." <info@bytewax.io>
License: # Software License Agreement
Project-URL: Homepage, https://github.com/bytewax/bytewax-rerun
Project-URL: Bug Reports, https://github.com/bytewax/bytewax-rerun/issues/new
Project-URL: Source, https://github.com/bytewax/bytewax-rerun/
Keywords: bytewax,streaming,operator
Classifier: Development Status :: 4 - Beta
Classifier: Intended Audience :: Developers
Classifier: Programming Language :: Python :: 3
Classifier: Programming Language :: Python :: 3.9
Classifier: Programming Language :: Python :: 3.10
Classifier: Programming Language :: Python :: 3.11
Classifier: Programming Language :: Python :: 3.12
Classifier: Programming Language :: Python :: 3 :: Only
Requires-Python: >=3.9
License-File: LICENSE.md
Requires-Dist: bytewax>=0.21
Requires-Dist: rerun-sdk>=0.18
